{
	"version": "0.3.17", 
	"suite": "unknown_suite", 
	"function_id": 18, 
	"function_name": "LABS", 
	"maximization": true, 
	"algorithm": {"name": "genetic_algorithm", "info": "Practical assignment of the EA course"},
	"attributes": ["evaluations", "raw_y"],
	"scenarios": [
		{"dimension": 50,
		"path": "data_f18_LABS/IOHprofiler_f18_DIM50.dat",
		"runs": [
			{"instance": 1, "evals": 5000, "best": {"evals": 2511, "y": 3.056234718826406, "x": [0, 1, 1, 0, 0, 0, 1, 0, 1, 0, 1, 0, 1, 0, 0, 1, 1, 0, 1, 1, 0, 0, 0, 1, 0, 1, 1, 0, 0, 0, 0, 0, 0, 0, 1, 1, 0, 1, 1, 1, 1, 1, 0, 0, 1, 1, 1, 0, 0, 1]}},
			{"instance": 1, "evals": 5000, "best": {"evals": 3943, "y": 2.886836027713626, "x": [1, 0, 1, 0, 0, 1, 0, 1, 0, 0, 1, 1, 0, 1, 0, 0, 0, 1, 0, 1, 1, 1, 1, 0, 0, 0, 1, 1, 1, 1, 0, 1, 1, 0, 0, 1, 0, 0, 0, 0, 0, 0, 0, 0, 1, 1, 0, 0, 1, 1]}},
			{"instance": 1, "evals": 5000, "best": {"evals": 4534, "y": 3.056234718826406, "x": [0, 0, 1, 1, 1, 1, 0, 0, 0, 1, 1, 0, 1, 0, 0, 1, 0, 0, 1, 0, 1, 1, 0, 1, 1, 0, 0, 1, 1, 0, 0, 1, 1, 0, 1, 0, 1, 0, 1, 0, 1, 1, 1, 1, 1, 1, 1, 1, 1, 1]}},
			{"instance": 1, "evals": 5000, "best": {"evals": 4027, "y": 3.4626038781163433, "x": [0, 1, 0, 1, 1, 1, 0, 1, 0, 0, 1, 1, 1, 1, 0, 0, 1, 0, 1, 1, 0, 1, 0, 1, 0, 0, 1, 0, 0, 0, 1, 1, 0, 0, 0, 1, 1, 0, 0, 1, 1, 0, 1, 0, 0, 0, 0, 0, 0, 0]}},
			{"instance": 1, "evals": 5000, "best": {"evals": 1907, "y": 3.315649867374005, "x": [1, 1, 0, 1, 1, 1, 1, 1, 0, 0, 1, 0, 1, 1, 0, 1, 1, 1, 1, 1, 0, 0, 1, 1, 0, 0, 1, 1, 0, 1, 0, 1, 0, 1, 0, 0, 0, 0, 0, 1, 1, 1, 1, 0, 1, 0, 1, 1, 1, 1]}},
			{"instance": 1, "evals": 5000, "best": {"evals": 3063, "y": 2.9411764705882355, "x": [0, 0, 1, 1, 1, 0, 1, 0, 0, 1, 1, 0, 1, 0, 1, 1, 1, 0, 1, 1, 0, 0, 0, 0, 1, 0, 1, 0, 1, 1, 0, 0, 0, 0, 0, 1, 0, 1, 1, 1, 1, 0, 1, 1, 1, 1, 1, 1, 0, 0]}},
			{"instance": 1, "evals": 5000, "best": {"evals": 3084, "y": 2.7839643652561246, "x": [0, 0, 0, 1, 1, 1, 1, 0, 0, 0, 0, 0, 1, 0, 0, 0, 1, 1, 1, 0, 1, 1, 1, 0, 1, 1, 1, 1, 1, 0, 0, 1, 0, 0, 1, 0, 1, 1, 0, 1, 0, 1, 1, 0, 1, 1, 1, 0, 1, 1]}},
			{"instance": 1, "evals": 5000, "best": {"evals": 1312, "y": 3.315649867374005, "x": [1, 0, 1, 1, 0, 1, 1, 1, 1, 1, 1, 0, 1, 1, 0, 1, 0, 0, 1, 0, 0, 0, 0, 0, 1, 1, 1, 1, 0, 0, 0, 0, 1, 0, 0, 1, 1, 1, 0, 1, 0, 1, 0, 1, 0, 0, 0, 1, 1, 0]}},
			{"instance": 1, "evals": 5000, "best": {"evals": 2719, "y": 2.735229759299781, "x": [1, 0, 1, 1, 1, 0, 0, 1, 1, 1, 1, 0, 1, 1, 0, 1, 0, 0, 1, 1, 1, 1, 1, 1, 0, 1, 1, 0, 0, 0, 1, 0, 1, 0, 0, 0, 0, 0, 1, 1, 1, 1, 1, 0, 1, 0, 1, 1, 0, 0]}},
			{"instance": 1, "evals": 5000, "best": {"evals": 3888, "y": 3.1806615776081424, "x": [0, 0, 1, 0, 0, 0, 0, 0, 0, 1, 1, 1, 1, 0, 1, 0, 1, 1, 0, 0, 1, 1, 0, 0, 0, 1, 1, 0, 1, 1, 0, 0, 1, 0, 1, 1, 1, 1, 1, 1, 0, 1, 1, 0, 0, 1, 0, 1, 1, 1]}}
		]}
	]
}
